calculadorasimplesthiago/__init__.py
calculadorasimplesthiago/calculadorasimples.py
calculadorasimplesthiago/myfunctions.py
calculadorasimplesthiago-0.1.0.dist-info/METADATA
calculadorasimplesthiago-0.1.0.dist-info/WHEEL
calculadorasimplesthiago-0.1.0.dist-info/top_level.txt
calculadorasimplesthiago-0.1.0.dist-info/RECORD
