Metadata-Version: 2.4
Name: calculadorasimplesthiago
Version: 0.1.0
Summary: calculadora para atividade projetos de sistemas
Author: Eu
License: MIT
Dynamic: author
Dynamic: license
Dynamic: summary
